LICENSE
README.md
setup.cfg
setup.py
playingcards/__init__.py
playingcards/main.py
playingcards/utils.py
playingcards1598.egg-info/PKG-INFO
playingcards1598.egg-info/SOURCES.txt
playingcards1598.egg-info/dependency_links.txt
playingcards1598.egg-info/top_level.txt