Metadata-Version: 2.1
Name: playingcards1598
Version: 1.1.8
Summary: An Advanced and Customisable Python Playing Card Module that makes creating playing card games and running simulations general, simple and easy!
Home-page: https://github.com/mitchr1598/playingcards
Author: mitchr1598
License: MIT
Platform: UNKNOWN
Classifier: License :: OSI Approved :: MIT License
Requires-Python: >=3.9.0
License-File: LICENSE
